VS/Electronica_Avanzada/VHDL/FSM_encoder_direccion/FSM_encoder_direccion.vhd
library IEEE;
use IEEE.STD_LOGIC_1164.ALL;

entity FSM_encoder_direccion is
    Port (
        RST       : in  STD_LOGIC;
        CLK       : in  STD_LOGIC;
        A         : in  STD_LOGIC;
        B         : in  STD_LOGIC;
        S         : out STD_LOGIC
    );
end FSM_encoder_direccion;

architecture FSM of FSM_encoder_direccion is
    type state_type is (S0, S1, S2, S3, S4, S5, S6, S7);
    signal state, s_siguiente : state_type;
    signal concat_signal : STD_LOGIC_VECTOR(1 downto 0);
begin

    process(state, A, B)
    begin
        concat_signal <= A & B;
        case state is
            when S0 =>
                case concat_signal is
                    when "00" => s_siguiente <= S0;
                    when "01" => s_siguiente <= S1;
                    when "10" => s_siguiente <= S4;
                    when "11" => s_siguiente <= S0;
                    when others => s_siguiente <= S0;
                end case;
                S <= '0';
                
            when S1 =>
                case concat_signal is
                    when "00" => s_siguiente <= S5;
                    when "01" => s_siguiente <= S1;
                    when "10" => s_siguiente <= S1;
                    when "11" => s_siguiente <= S2;
                    when others => s_siguiente <= S0;
                end case;
                S <= '0';

            when S2 =>
                case concat_signal is
                    when "00" => s_siguiente <= S2;
                    when "01" => s_siguiente <= S6;
                    when "10" => s_siguiente <= S3;
                    when "11" => s_siguiente <= S2;
                    when others => s_siguiente <= S0;
                end case;
                S <= '0';
                
            when S3 =>
                case concat_signal is
                    when "00" => s_siguiente <= S0;
                    when "01" => s_siguiente <= S3;
                    when "10" => s_siguiente <= S3;
                    when "11" => s_siguiente <= S7;
                    when others => s_siguiente <= S0;
                end case;
                S <= '0';

            when S4 =>
                case concat_signal is
                    when "00" => s_siguiente <= S0;
                    when "01" => s_siguiente <= S4;
                    when "10" => s_siguiente <= S4;
                    when "11" => s_siguiente <= S7;
                    when others => s_siguiente <= S0;
                end case;
                S <= '1';

            when S5 =>
                case concat_signal is
                    when "00" => s_siguiente <= S5;
                    when "01" => s_siguiente <= S1;
                    when "10" => s_siguiente <= S4;
                    when "11" => s_siguiente <= S5;
                    when others => s_siguiente <= S0;
                end case;
                S <= '1';

            when S6 =>
                case concat_signal is
                    when "00" => s_siguiente <= S5;
                    when "01" => s_siguiente <= S6;
                    when "10" => s_siguiente <= S6;
                    when "11" => s_siguiente <= S2;
                    when others => s_siguiente <= S0;
                end case;
                S <= '1';

            when S7 =>
                case concat_signal is
                    when "00" => s_siguiente <= S7;
                    when "01" => s_siguiente <= S6;
                    when "10" => s_siguiente <= S3;
                    when "11" => s_siguiente <= S7;
                    when others => s_siguiente <= S0;
                end case;
                S <= '1';
                
            when others =>
                s_siguiente <= S0;
                S <= '0';
        end case;
    end process;
    
    process(CLK, RST)
    begin
        if RST = '1' then
            state <= S0;
        elsif rising_edge(CLK) then
            state <= s_siguiente;
        end if;
    end process;
    
end FSM;

VS/Electronica_Avanzada/VHDL/FSM_encoder_direccion/tb_FSM_encoder_direccion.vhd
library IEEE;
use IEEE.STD_LOGIC_1164.ALL;

entity tb_FSM_encoder_direccion is
end tb_FSM_encoder_direccion;

architecture behavior of tb_FSM_encoder_direccion is
    component FSM_encoder_direccion
        Port (
            RST : in  STD_LOGIC;
            CLK : in  STD_LOGIC;
            A   : in  STD_LOGIC;
            B   : in  STD_LOGIC;
            S   : out STD_LOGIC
        );
    end component;

    signal RST       : STD_LOGIC := '0';
    signal CLK       : STD_LOGIC := '0';
    signal A         : STD_LOGIC := '0';
    signal B         : STD_LOGIC := '0';
    signal S         : STD_LOGIC;

    constant CLK_PERIOD : time := 10 ns;

begin
    uut: FSM_encoder_direccion
        Port map (
            RST => RST,
            CLK => CLK,
            A   => A,
            B   => B,
            S   => S
        );

    clk_process : process
    begin
        CLK <= '0';
        wait for CLK_PERIOD / 2;
        CLK <= '1';
        wait for CLK_PERIOD / 2;
    end process;

    signal_tb : process
    begin
        RST <= '1';
        wait for 20 ns;
        RST <= '0';

        A <= '0'; B <= '0';
        wait for CLK_PERIOD * 10;

        A <= '0'; B <= '1';
        wait for CLK_PERIOD * 10;

        A <= '1'; B <= '0';
        wait for CLK_PERIOD * 10;

        A <= '1'; B <= '1';
        wait for CLK_PERIOD * 10;

        A <= '0'; B <= '1';
        wait for CLK_PERIOD * 10;

        A <= '1'; B <= '0';
        wait for CLK_PERIOD * 10;

        A <= '1'; B <= '1';
        wait for CLK_PERIOD * 10;

        A <= '0'; B <= '0';
        wait for CLK_PERIOD * 10;

        wait;
    end process;

end behavior;

VS/Electronica_Avanzada/VHDL/FSM_encoder_direccion/output.vcd
$date
  Thu Sep 12 18:46:01 2024
$end
$version
  GHDL v0
$end
$timescale
  1 fs
$end
$scope module standard $end
$upscope $end
$scope module std_logic_1164 $end
$upscope $end
$scope module tb_fsm_encoder_direccion $end
$var reg 1 ! rst $end
$var reg 1 " clk $end
$var reg 1 # a $end
$var reg 1 $ b $end
$var reg 1 % s $end
$scope module uut $end
$var reg 1 & rst $end
$var reg 1 ' clk $end
$var reg 1 ( a $end
$var reg 1 ) b $end
$var reg 1 * s $end
$comment state is not handled $end
$comment s_siguiente is not handled $end
$var reg 2 + concat_signal[1:0] $end
$upscope $end
$upscope $end
$enddefinitions $end
#0
1!
0"
0#
0$
0%
1&
0'
0(
0)
0*
b00 +
#5000000
1"
1'
#10000000
0"
0'
#15000000
1"
1'
#20000000
0!
0"
0&
0'
#25000000
1"
1'
#30000000
0"
0'
#35000000
1"
1'
#40000000
0"
0'
#45000000
1"
1'
#50000000
0"
0'
#55000000
1"
1'
#60000000
0"
0'
#65000000
1"
1'
#70000000
0"
0'
#75000000
1"
1'
#80000000
0"
0'
#85000000
1"
1'
#90000000
0"
0'
#95000000
1"
1'
#100000000
0"
0'
#105000000
1"
1'
#110000000
0"
0'
#115000000
1"
1'
#120000000
0"
1$
0'
1)
b01 +
#125000000
1"
1'
#130000000
0"
0'
#135000000
1"
1'
#140000000
0"
0'
#145000000
1"
1'
#150000000
0"
0'
#155000000
1"
1'
#160000000
0"
0'
#165000000
1"
1'
#170000000
0"
0'
#175000000
1"
1'
#180000000
0"
0'
#185000000
1"
1'
#190000000
0"
0'
#195000000
1"
1'
#200000000
0"
0'
#205000000
1"
1'
#210000000
0"
0'
#215000000
1"
1'
#220000000
0"
1#
0$
0'
1(
0)
b10 +
#225000000
1"
1'
#230000000
0"
0'
#235000000
1"
1'
#240000000
0"
0'
#245000000
1"
1'
#250000000
0"
0'
#255000000
1"
1'
#260000000
0"
0'
#265000000
1"
1'
#270000000
0"
0'
#275000000
1"
1'
#280000000
0"
0'
#285000000
1"
1'
#290000000
0"
0'
#295000000
1"
1'
#300000000
0"
0'
#305000000
1"
1'
#310000000
0"
0'
#315000000
1"
1'
#320000000
0"
1$
0'
1)
b11 +
#325000000
1"
1'
#330000000
0"
0'
#335000000
1"
1'
#340000000
0"
0'
#345000000
1"
1'
#350000000
0"
0'
#355000000
1"
1'
#360000000
0"
0'
#365000000
1"
1'
#370000000
0"
0'
#375000000
1"
1'
#380000000
0"
0'
#385000000
1"
1'
#390000000
0"
0'
#395000000
1"
1'
#400000000
0"
0'
#405000000
1"
1'
#410000000
0"
0'
#415000000
1"
1'
#420000000
0"
0#
0'
0(
b01 +
#425000000
1"
1'
#430000000
0"
0'
#435000000
1"
1%
1'
1*
#440000000
0"
0'
#445000000
1"
1'
#450000000
0"
0'
#455000000
1"
1'
#460000000
0"
0'
#465000000
1"
1'
#470000000
0"
0'
#475000000
1"
1'
#480000000
0"
0'
#485000000
1"
1'
#490000000
0"
0'
#495000000
1"
1'
#500000000
0"
0'
#505000000
1"
1'
#510000000
0"
0'
#515000000
1"
1'
#520000000
0"
1#
0$
0'
1(
0)
b10 +
#525000000
1"
1'
#530000000
0"
0'
#535000000
1"
1'
#540000000
0"
0'
#545000000
1"
1'
#550000000
0"
0'
#555000000
1"
1'
#560000000
0"
0'
#565000000
1"
1'
#570000000
0"
0'
#575000000
1"
1'
#580000000
0"
0'
#585000000
1"
1'
#590000000
0"
0'
#595000000
1"
1'
#600000000
0"
0'
#605000000
1"
1'
#610000000
0"
0'
#615000000
1"
1'
#620000000
0"
1$
0'
1)
b11 +
#625000000
1"
1'
#630000000
0"
0'
#635000000
1"
1'
#640000000
0"
0'
#645000000
1"
1'
#650000000
0"
0'
#655000000
1"
1'
#660000000
0"
0'
#665000000
1"
1'
#670000000
0"
0'
#675000000
1"
1'
#680000000
0"
0'
#685000000
1"
1'
#690000000
0"
0'
#695000000
1"
1'
#700000000
0"
0'
#705000000
1"
1'
#710000000
0"
0'
#715000000
1"
1'
#720000000
0"
0#
0$
0'
0(
0)
b00 +
