VS/Electronica_Avanzada/VHDL/Contador/contador.vhd
library IEEE;
use IEEE.STD_LOGIC_1164.ALL;
use IEEE.NUMERIC_STD.ALL;

-- Definición de la entidad
entity ContDes is
    generic(n : integer := 4);
    port(
        RST : in std_logic;
        CLK : in std_logic;
        OPC : in std_logic_vector(1 downto 0);
        K   : in std_logic_vector(n-1 downto 0);
        Z   : out std_logic;
        Q   : out std_logic_vector(n-1 downto 0)
    );
end ContDes;

-- Definición de la arquitectura
architecture contar of ContDes is
    signal Qp, Qn, Zr : std_logic_vector(n-1 downto 0);

begin
    Q <= Qp;
    Zr <= (others => '0'); -- others -> todos los bits
    Z <= '1' when Qp = Zr else '0';
    
    -- OPC | Qn
    -- ------------
    -- 00 | Qp    Hold
    -- 01 | Qp-1  Decrement
    -- 1x | K     Load
    
    mux : process(OPC, Qn, K)
    begin
        if OPC(1) = '1' then
            Qn <= K;
        elsif OPC(0) = '1' then
            Qn <= std_logic_vector(unsigned(Qp) - 1);
        else
            Qn <= Qp;
        end if;
    end process mux;
    
    Qp <= (others => '0') when RST = '1' else Qn when rising_edge(CLK);
end contar;

VS/Electronica_Avanzada/VHDL/Contador/tb_ContDes.vhd
library IEEE;
use IEEE.STD_LOGIC_1164.ALL;
use IEEE.NUMERIC_STD.ALL;

-- Definición de la entidad
entity tb_ContDes is
end tb_ContDes;

-- Definición de la arquitectura
architecture behavior of tb_ContDes is
    -- Declaración de señales
    signal RST : std_logic := '0';
    signal CLK : std_logic := '0';
    signal OPC : std_logic_vector(1 downto 0) := "00";
    signal K   : std_logic_vector(3 downto 0) := "0000";
    signal Z   : std_logic;
    signal Q   : std_logic_vector(3 downto 0);

    -- Periodo del reloj
    constant CLK_PERIOD : time := 20 ns;

begin
    uut: entity work.ContDes
        generic map (n => 4)
        port map (
            RST => RST,
            CLK => CLK,
            OPC => OPC,
            K   => K,
            Z   => Z,
            Q   => Q
        );

    -- Generación del reloj
    clk_process : process
    begin
        CLK <= '0';
        wait for CLK_PERIOD / 2;
        CLK <= '1';
        wait for CLK_PERIOD / 2;
    end process;

    -- Proceso de estímulo
    stimulus_process : process
    begin
        -- Inicialización
        RST <= '1';
        OPC <= "00";
        K <= "0101";
        wait for 40 ns;
        
        -- Desactivación del reset
        RST <= '0';
        wait for 20 ns;
        
        -- OPC = "00", mantener el valor actual
        OPC <= "00";
        wait for 140 ns;
        
        -- OPC = "10", cargar el valor de K
        OPC <= "10";
        K <= "1001";  -- Ejemplo de valor para K
        wait for 40 ns;
        
        -- OPC = "00", mantener el valor actual
        OPC <= "00";
        wait for 40 ns;
        
        -- OPC = "01", decrementar
        OPC <= "01";
        wait for 40 ns;
        
        -- OPC = "00", mantener el valor actual
        OPC <= "00";
        wait for 40 ns;
        
        -- OPC = "01", decrementar
        OPC <= "01";
        wait for 40 ns;
        
        -- OPC = "00", mantener el valor actual
        OPC <= "00";
        wait for 40 ns;
        
        -- OPC = "01", decrementar
        OPC <= "01";
        wait for 40 ns;
        
        -- OPC = "00", mantener el valor actual
        OPC <= "00";
        wait for 40 ns;
        
        -- OPC = "01", decrementar
        OPC <= "01";
        wait for 40 ns;
        
        -- OPC = "00", mantener el valor actual
        OPC <= "00";
        wait for 40 ns;
        
        -- Detener la simulación
        wait;
    end process;

end behavior;

VS/Electronica_Avanzada/VHDL/Contador/tb_ContDes.vcd
$date
  Thu Aug 29 17:45:42 2024
$end
$version
  GHDL v0
$end
$timescale
  1 fs
$end
$scope module standard $end
$upscope $end
$scope module std_logic_1164 $end
$upscope $end
$scope module numeric_std $end
$upscope $end
$scope module tb_contdes $end
$var reg 1 ! rst $end
$var reg 1 " clk $end
$var reg 2 # opc[1:0] $end
$var reg 4 $ k[3:0] $end
$var reg 1 % z $end
$var reg 4 & q[3:0] $end
$scope module uut $end
$var reg 1 ' rst $end
$var reg 1 ( clk $end
$var reg 2 ) opc[1:0] $end
$var reg 4 * k[3:0] $end
$var reg 1 + z $end
$var reg 4 , q[3:0] $end
$var reg 4 - qp[3:0] $end
$var reg 4 . qn[3:0] $end
$var reg 4 / zr[3:0] $end
$upscope $end
$upscope $end
$enddefinitions $end
#0
1!
0"
b00 #
b0101 $
1%
b0000 &
1'
0(
b00 )
b0101 *
1+
b0000 ,
b0000 -
bUUUU .
b0000 /
#10000000
1"
1(
#20000000
0"
0(
#30000000
1"
1(
#40000000
0!
0"
0'
0(
#50000000
1"
0%
bUUUU &
1(
0+
bUUUU ,
bUUUU -
#60000000
0"
0(
#70000000
1"
1(
#80000000
0"
0(
#90000000
1"
1(
#100000000
0"
0(
#110000000
1"
1(
#120000000
0"
0(
#130000000
1"
1(
#140000000
0"
0(
#150000000
1"
1(
#160000000
0"
0(
#170000000
1"
1(
#180000000
0"
0(
#190000000
1"
1(
#200000000
0"
b10 #
b1001 $
0(
b10 )
b1001 *
b1001 .
#210000000
1"
b1001 &
1(
b1001 ,
b1001 -
#220000000
0"
0(
#230000000
1"
1(
#240000000
0"
b00 #
0(
b00 )
#250000000
1"
1(
#260000000
0"
0(
#270000000
1"
1(
#280000000
0"
b01 #
0(
b01 )
b1000 .
#290000000
1"
b1000 &
1(
b1000 ,
b1000 -
#300000000
0"
0(
#310000000
1"
1(
#320000000
0"
b00 #
0(
b00 )
#330000000
1"
1(
#340000000
0"
0(
#350000000
1"
1(
#360000000
0"
b01 #
0(
b01 )
b0111 .
#370000000
1"
b0111 &
1(
b0111 ,
b0111 -
#380000000
0"
0(
#390000000
1"
1(
#400000000
0"
b00 #
0(
b00 )
#410000000
1"
1(
#420000000
0"
0(
#430000000
1"
1(
#440000000
0"
b01 #
0(
b01 )
b0110 .
#450000000
1"
b0110 &
1(
b0110 ,
b0110 -
#460000000
0"
0(
#470000000
1"
1(
#480000000
0"
b00 #
0(
b00 )
#490000000
1"
1(
#500000000
0"
0(
#510000000
1"
1(
#520000000
0"
b01 #
0(
b01 )
b0101 .
#530000000
1"
b0101 &
1(
b0101 ,
b0101 -
#540000000
0"
0(
#550000000
1"
1(
#560000000
0"
b00 #
0(
b00 )
